muzzle/__init__.py
muzzle/errors.py
muzzle/xmlparse.py
muzzle-0.0.1.dist-info/LICENSE.md
muzzle-0.0.1.dist-info/WHEEL
muzzle-0.0.1.dist-info/METADATA
muzzle-0.0.1.dist-info/RECORD
