Metadata-Version: 2.1
Name: muzzle
Version: 0.0.1
Summary: A tiny xmlparser
Author-email: Stefan Oderbolz <odi@metaodi.ch>
Requires-Python: >=3.7
Classifier: License :: OSI Approved :: MIT License
Requires-Dist: defusedxml
Requires-Dist: xmltodict
Requires-Dist: flit ; extra == "dev"
Requires-Dist: flake8 ; extra == "test"
Requires-Dist: mock ; extra == "test"
Requires-Dist: pytest ; extra == "test"
Requires-Dist: pytest-cov ; extra == "test"
Project-URL: Home, https://github.com/metaodi/muzzle
Provides-Extra: dev
Provides-Extra: test
